[
  {
    "name": "build-deps",
    "archived": false,
    "releases": [
      {
        "tag": "v2026.425.130933",
        "assetCount": 22
      },
      {
        "tag": "v2026.323.141148",
        "assetCount": 18
      },
      {
        "tag": "v2026.221.143859",
        "assetCount": 18
      },
      {
        "tag": "v2026.209.233149",
        "assetCount": 18
      }
    ]
  },
  {
    "name": "libdisplaydevice",
    "archived": false,
    "releases": [
      {
        "tag": "v2026.322.2407",
        "assetCount": 2
      },
      {
        "tag": "v2025.411.113543",
        "assetCount": 2
      },
      {
        "tag": "v2025.115.133852",
        "assetCount": 2
      },
      {
        "tag": "v2024.1217.151047",
        "assetCount": 2
      },
      {
        "tag": "v2024.1116.222346",
        "assetCount": 2
      },
      {
        "tag": "v2024.807.213004",
        "assetCount": 2
      }
    ]
  }
]